rusty_tags/__init__.py
rusty_tags/__init__.pyi
rusty_tags/core.cpython-311-darwin.so
rusty_tags/datastar.py
rusty_tags/utils.py
rusty_tags-0.6.36.dist-info/METADATA
rusty_tags-0.6.36.dist-info/WHEEL
rusty_tags-0.6.36.dist-info/RECORD
