Metadata-Version: 2.4
Name: rusty_tags
Version: 0.6.36
Classifier: Development Status :: 4 - Beta
Classifier: Intended Audience :: Developers
Classifier: License :: OSI Approved :: MIT License
Classifier: Programming Language :: Python :: 3
Classifier: Programming Language :: Python :: 3.10
Classifier: Programming Language :: Python :: 3.11
Classifier: Programming Language :: Python :: 3.12
Classifier: Programming Language :: Python :: 3.13
Classifier: Programming Language :: Python :: 3.14
Classifier: Programming Language :: Rust
Classifier: Programming Language :: Python :: Implementation :: CPython
Classifier: Programming Language :: Python :: Implementation :: PyPy
Classifier: Topic :: Internet :: WWW/HTTP :: Dynamic Content
Classifier: Topic :: Software Development :: Libraries :: Python Modules
Classifier: Topic :: Text Processing :: Markup :: HTML
Requires-Dist: datastar-py>=0.6.5
Summary: Core HTML generation library with Rust-based Python extension - high performance, minimal dependencies
Keywords: html,svg,performance,rust,core,generation
Author: RustyTags Contributors
License: MIT
Requires-Python: >=3.10
Project-URL: Homepage, https://github.com/ndendic/rustyTags
Project-URL: Issues, https://github.com/ndendic/rustyTags/issues
Project-URL: Repository, https://github.com/ndendic/rustyTags
